readme.md
requirements.txt
setup.py
easy_spider/__init__.py
easy_spider/log.py
easy_spider/tool.py
easy_spider.egg-info/PKG-INFO
easy_spider.egg-info/SOURCES.txt
easy_spider.egg-info/dependency_links.txt
easy_spider.egg-info/requires.txt
easy_spider.egg-info/top_level.txt
easy_spider/core/__init__.py
easy_spider/core/env.py
easy_spider/core/queue.py
easy_spider/core/recoverable.py
easy_spider/core/spider.py
easy_spider/core/task.py
easy_spider/error/__init__.py
easy_spider/error/error_formatter.py
easy_spider/error/error_handler.py
easy_spider/error/known_error.py
easy_spider/extractors/__init__.py
easy_spider/extractors/extractor.py
easy_spider/filters/__init__.py
easy_spider/filters/build_in.py
easy_spider/filters/filter.py
easy_spider/filters/history_filter.py
easy_spider/middlewares/__init__.py
easy_spider/middlewares/build_in.py
easy_spider/network/__init__.py
easy_spider/network/client.py
easy_spider/network/request.py
easy_spider/network/response.py
test/test_env.py
test/test_exception_handler.py
test/test_extractor.py
test/test_filter.py
test/test_middlewares.py
test/test_network.py
test/test_spider.py
test/test_task.py
test/test_tool.py