Metadata-Version: 2.1
Name: easy-spider
Version: 1.1.2
Summary: A asynchronous spider with aiohttp
Home-page: https://lin3x.coding.net/p/easy_spider
Author: lin3x
Author-email: 544670411@qq.com
License: UNKNOWN
Platform: UNKNOWN
Classifier: Programming Language :: Python :: 3
Classifier: License :: OSI Approved :: MIT License
Classifier: Operating System :: OS Independent
